edge_assistant/__init__.py
edge_assistant/cli.py
edge_assistant/engine.py
edge_assistant/state.py
edge_assistant/tools.py
edge_assistant-0.1.0.dist-info/licenses/LICENSE
edge_assistant-0.1.0.dist-info/METADATA
edge_assistant-0.1.0.dist-info/WHEEL
edge_assistant-0.1.0.dist-info/entry_points.txt
edge_assistant-0.1.0.dist-info/top_level.txt
edge_assistant-0.1.0.dist-info/RECORD
